[{"id":0,"name":"Default Elipse Shape 1","shapeType":"ElipseShape","diameterX":300.0,"diameterY":200.0,"diameter":0.0},{"id":1,"name":"Default Elipse Shape 2","shapeType":"ElipseShape","diameterX":200.0,"diameterY":300.0,"diameter":0.0},{"id":2,"name":"Rectangle 1","shapeType":"OtherShape","diameterX":0.0,"diameterY":0.0,"points":[{"x":256,"y":150},{"x":556,"y":150},{"x":556,"y":300},{"x":256,"y":300}],"diameter":0.0},{"id":3,"name":"Rectangle 2","shapeType":"OtherShape","diameterX":0.0,"diameterY":0.0,"points":[{"x":256,"y":150},{"x":356,"y":150},{"x":356,"y":450},{"x":256,"y":450}],"diameter":0.0},{"id":4,"name":"2Circle","shapeType":"CircleShape","diameterX":0.0,"diameterY":0.0,"diameter":200.0}]